{
  "@context": "https://schema.org",
  "@type": "FAQPage",
  "@id": "https://mospochin.ru/holodilnye-vitriny-i-gorki.html#faq",
  "url": "https://mospochin.ru/holodilnye-vitriny-i-gorki.html",
  "name": "Ремонт холодильных витрин и горок | MosPochin",
  "mainEntity": [
    {
      "@type": "Question",
      "name": "Почему нельзя ставить товар вплотную к решёткам?",
      "acceptedAnswer": {
        "@type": "Answer",
        "text": "Товар нарушает подачу или возврат воздуха и разрушает воздушную завесу."
      }
    },
    {
      "@type": "Question",
      "name": "Почему горка хуже работает при открытой двери магазина?",
      "acceptedAnswer": {
        "@type": "Answer",
        "text": "Сквозняк и тёплый влажный воздух увеличивают тепловую и влажностную нагрузку."
      }
    },
    {
      "@type": "Question",
      "name": "Достаточно ли измерять температуру по дисплею?",
      "acceptedAnswer": {
        "@type": "Answer",
        "text": "Нет. Проверяется температура продукта и разных зон выкладки, поскольку датчик контроллера находится в одной точке."
      }
    }
  ]
}
