{
  "@context": "https://schema.org",
  "@type": "FAQPage",
  "@id": "https://mospochin.ru/posudomoechnaya-mashina-ostanavlivaetsya-v-cikle.html#faq",
  "url": "https://mospochin.ru/posudomoechnaya-mashina-ostanavlivaetsya-v-cikle.html",
  "name": "Посудомоечная машина останавливается в цикле | MosPochin",
  "mainEntity": [
    {
      "@type": "Question",
      "name": "Почему после перезапуска машина проходит цикл?",
      "acceptedAnswer": {
        "@type": "Answer",
        "text": "Нестабильная блокировка, датчик, перегрев двигателя или связь могут временно восстанавливаться. Нужна проверка в момент отказа."
      }
    },
    {
      "@type": "Question",
      "name": "Полезно ли записать оставшееся время?",
      "acceptedAnswer": {
        "@type": "Answer",
        "text": "Да. Время и стадия помогают понять, какой узел должен был включиться перед остановкой."
      }
    },
    {
      "@type": "Question",
      "name": "Можно ли замкнуть датчик двери для проверки?",
      "acceptedAnswer": {
        "@type": "Answer",
        "text": "Нет. Обход защитной цепи опасен и искажает диагностику."
      }
    }
  ]
}
