{
  "@context": "https://schema.org",
  "@type": "FAQPage",
  "@id": "https://mospochin.ru/posudomoechnaya-mashina-ne-nabiraet-vodu.html#faq",
  "url": "https://mospochin.ru/posudomoechnaya-mashina-ne-nabiraet-vodu.html",
  "name": "Посудомоечная машина не набирает воду — диагностика и ремонт | MosPochin",
  "mainEntity": [
    {
      "@type": "Question",
      "name": "Можно ли продолжать ждать, если машина долго набирает воду?",
      "acceptedAnswer": {
        "@type": "Answer",
        "text": "Повторяющееся превышение времени наполнения указывает на недостаточный поток или неисправность. Цикл лучше остановить и зафиксировать условия."
      }
    },
    {
      "@type": "Question",
      "name": "Если слышен клапан, он исправен?",
      "acceptedAnswer": {
        "@type": "Answer",
        "text": "Щелчок подтверждает только срабатывание привода. Поток может блокировать сетка, давление, шланг или механическая часть клапана."
      }
    },
    {
      "@type": "Question",
      "name": "Почему вода есть, но ошибка не исчезает?",
      "acceptedAnswer": {
        "@type": "Answer",
        "text": "Контроллер может не получать корректный сигнал уровня. Проверяют датчик, трубки и конфигурацию конкретной модели."
      }
    }
  ]
}
