{
  "subtitle": "🔧 Ресторанное оборудование",
  "contactHint": "⚡ Работаем по согласованному графику",
  "topBarText": {
    "icon": "ri-flashlight-fill",
    "text": "🚨 СРОЧНАЯ ЗАЯВКА",
    "sub": "Следующий шаг согласуем после уточнения задачи"
  },
  "services": [
    {
      "href": "uslugi.html",
      "icon": "🔧",
      "name": "Все услуги"
    },
    {
      "href": "parokonvektomaty.html",
      "icon": "🔥",
      "name": "Пароконвектоматы"
    },
    {
      "href": "plity-pechi.html",
      "icon": "🍳",
      "name": "Плиты и печи"
    },
    {
      "href": "holodilnoe-oborudovanie.html",
      "icon": "❄️",
      "name": "Холодильное оборудование"
    },
    {
      "href": "posudomoechnye-mashiny.html",
      "icon": "🍽️",
      "name": "Посудомойки"
    },
    {
      "href": "ventilyatsiya-restoranov.html",
      "icon": "🌬️",
      "name": "Вентиляция ресторанов"
    },
    {
      "href": "grili-mangaly.html",
      "icon": "🍳",
      "name": "Грили и фритюр"
    },
    {
      "href": "ice-machines.html",
      "icon": "🧊",
      "name": "Льдогенераторы"
    },
    {
      "href": "pishevarochnye-kotly.html",
      "icon": "🥘",
      "name": "Пищеварочные котлы"
    },
    {
      "href": "pishevarochnyj-kotel-ne-greet.html",
      "icon": "🔥",
      "name": "Котел не греет"
    },
    {
      "href": "pishevarochnyj-kotel-techet.html",
      "icon": "💧",
      "name": "Течет котел"
    },
    {
      "href": "pishevarochnyj-kotel-vybivaet-avtomat.html",
      "icon": "⚡",
      "name": "Выбивает автомат"
    },
    {
      "href": "pishevarochnyj-kotel-kod-oshibki.html",
      "icon": "🧾",
      "name": "Код ошибки котла"
    },
    {
      "href": "pishevarochnyj-kotel-suhoy-hod.html",
      "icon": "🚰",
      "name": "Сухой ход / H2O"
    },
    {
      "href": "remont-pishevarochnyh-kotlov-kpem.html",
      "icon": "🏭",
      "name": "Abat КПЭМ"
    },
    {
      "href": "parokonvektomat-techet-voda.html",
      "icon": "ri-water-flash-line",
      "name": "Пароконвектомат течёт"
    },
    {
      "href": "parokonvektomat-ne-nabiraet-vodu.html",
      "icon": "ri-drop-line",
      "name": "Не набирает воду"
    },
    {
      "href": "parokonvektomat-ne-vklyuchaetsya.html",
      "icon": "ri-power-line",
      "name": "Не включается"
    },
    {
      "href": "pishevarochnyj-kotel-ne-nabiraet-vodu.html",
      "icon": "🔧",
      "name": "Котел не набирает воду"
    },
    {
      "href": "pishevarochnyj-kotel-ne-derzhit-davlenie.html",
      "icon": "🔧",
      "name": "Котел не держит давление"
    },
    {
      "href": "pishevarochnyj-kotel-ne-slivaet-vodu.html",
      "icon": "🔧",
      "name": "Котел не сливает воду"
    },
    {
      "href": "parokonvektomat-vybivaet-avtomat.html",
      "icon": "⚡",
      "name": "Выбивает автомат"
    },
    {
      "href": "parokonvektomat-ne-rabotaet-ventilyator.html",
      "icon": "🌀",
      "name": "Не работает вентилятор"
    },
    {
      "href": "parokonvektomat-ne-slivaet-vodu.html",
      "icon": "💧",
      "name": "Не сливает воду"
    },
    {
      "href": "parokonvektomat-ne-zakryvaetsya-dver.html",
      "icon": "🚪",
      "name": "Не закрывается дверь"
    },
    {
      "href": "dekalcinaciya-parokonvektomata.html",
      "icon": "🫧",
      "name": "Декальцинация"
    },
    {
      "href": "remont-platy-parokonvektomata.html",
      "icon": "🔌",
      "name": "Ремонт платы"
    },
    {
      "href": "remont-elektronnyh-plat-restorannogo-oborudovaniya.html",
      "icon": "🔬",
      "name": "Ремонт электронных плат"
    }
  ],
  "primaryServices": [
    {
      "href": "uslugi.html",
      "icon": "🔧",
      "name": "Все услуги"
    },
    {
      "href": "parokonvektomaty.html",
      "icon": "🔥",
      "name": "Пароконвектоматы"
    },
    {
      "href": "plity-pechi.html",
      "icon": "🍳",
      "name": "Плиты и печи"
    },
    {
      "href": "holodilnoe-oborudovanie.html",
      "icon": "❄️",
      "name": "Холодильное оборудование"
    },
    {
      "href": "posudomoechnye-mashiny.html",
      "icon": "🍽️",
      "name": "Посудомойки"
    },
    {
      "href": "ventilyatsiya-restoranov.html",
      "icon": "🌬️",
      "name": "Вентиляция ресторанов"
    }
  ],
  "footerLinks": [
    {
      "href": "index.html",
      "label": "Главная"
    },
    {
      "href": "uslugi.html",
      "label": "Услуги"
    },
    {
      "href": "parokonvektomaty.html",
      "label": "Пароконвектоматы"
    },
    {
      "href": "plity-pechi.html",
      "label": "Плиты и печи"
    },
    {
      "href": "holodilnoe-oborudovanie.html",
      "label": "Холодильное оборудование"
    },
    {
      "href": "posudomoechnye-mashiny.html",
      "label": "Посудомойки"
    },
    {
      "href": "ventilyatsiya-restoranov.html",
      "label": "Вентиляция ресторанов"
    },
    {
      "href": "grili-mangaly.html",
      "label": "Грили и фритюр"
    },
    {
      "href": "ice-machines.html",
      "label": "Льдогенераторы"
    },
    {
      "href": "pishevarochnye-kotly.html",
      "label": "Пищеварочные котлы"
    },
    {
      "href": "pishevarochnyj-kotel-ne-greet.html",
      "label": "Котел не греет"
    },
    {
      "href": "pishevarochnyj-kotel-techet.html",
      "label": "Течет котел"
    },
    {
      "href": "pishevarochnyj-kotel-vybivaet-avtomat.html",
      "label": "Выбивает автомат"
    },
    {
      "href": "pishevarochnyj-kotel-kod-oshibki.html",
      "label": "Код ошибки котла"
    },
    {
      "href": "pishevarochnyj-kotel-suhoy-hod.html",
      "label": "Сухой ход / H2O"
    },
    {
      "href": "remont-pishevarochnyh-kotlov-kpem.html",
      "label": "Abat КПЭМ"
    },
    {
      "href": "parokonvektomat-techet-voda.html",
      "label": "Пароконвектомат течёт"
    },
    {
      "href": "parokonvektomat-ne-nabiraet-vodu.html",
      "label": "Не набирает воду"
    },
    {
      "href": "parokonvektomat-ne-vklyuchaetsya.html",
      "label": "Не включается"
    },
    {
      "href": "pishevarochnyj-kotel-ne-nabiraet-vodu.html",
      "label": "Котел не набирает воду"
    },
    {
      "href": "pishevarochnyj-kotel-ne-derzhit-davlenie.html",
      "label": "Котел не держит давление"
    },
    {
      "href": "pishevarochnyj-kotel-ne-slivaet-vodu.html",
      "label": "Котел не сливает воду"
    },
    {
      "href": "about.html",
      "label": "О компании"
    },
    {
      "href": "contact.html",
      "label": "Контакты"
    },
    {
      "href": "remont-elektronnyh-plat-restorannogo-oborudovaniya.html",
      "label": "Ремонт электронных плат"
    }
  ],
  "routeStrips": {
    "index": {
      "badge": "БЫСТРЫЙ МАРШРУТ",
      "title": "Если уже знаете симптом, переходите сразу",
      "description": "Не нужно читать весь лендинг подряд. Выберите, что именно встало на кухне, и попадёте в нужную сервисную страницу.",
      "action": {
        "href": "uslugi.html",
        "label": "Полный каталог услуг",
        "icon": "ri-arrow-right-line"
      },
      "cards": [
        {
          "href": "parokonvektomaty.html",
          "title": "Ошибка у пароконвектомата",
          "description": "Rational, Unox, Electrolux, Abat"
        },
        {
          "href": "plity-pechi.html",
          "title": "Не греет горячая линия",
          "description": "Плиты, печи, шкафы, индукция"
        },
        {
          "href": "holodilnoe-oborudovanie.html",
          "title": "Не морозит или течёт",
          "description": "Шкафы, столы, витрины, камеры"
        },
        {
          "href": "posudomoechnye-mashiny.html",
          "title": "Не моет или не греет воду",
          "description": "Купольные, фронтальные, туннельные"
        },
        {
          "href": "ventilyatsiya-restoranov.html",
          "title": "Дым, запах или вытяжка не тянет",
          "description": "Вентиляция, вытяжка, приток, зонты, вентиляторы"
        }
      ]
    },
    "uslugi": {
      "badge": "БЫСТРЫЙ ВЫБОР",
      "title": "Начните с симптома, если техника уже встала",
      "description": "Этот хаб должен вести в нужное направление, а не заставлять читать всё подряд. Ниже быстрые маршруты по типовой проблеме кухни.",
      "action": {
        "href": "#full-services",
        "label": "Открыть полный список",
        "icon": "ri-arrow-down-line"
      },
      "cards": [
        {
          "href": "parokonvektomaty.html",
          "title": "Ошибка у пароконвектомата",
          "description": "Rational, Unox, Electrolux, Abat"
        },
        {
          "href": "plity-pechi.html",
          "title": "Не греет горячая линия",
          "description": "Плиты, печи, шкафы, индукция"
        },
        {
          "href": "holodilnoe-oborudovanie.html",
          "title": "Не морозит или течёт",
          "description": "Шкафы, столы, витрины, камеры"
        },
        {
          "href": "posudomoechnye-mashiny.html",
          "title": "Не моет или не греет воду",
          "description": "Фронтальные, купольные, туннельные"
        },
        {
          "href": "remont-ventilyatsii-restoranov.html",
          "title": "Дым, запах или вытяжка не тянет",
          "description": "Вентиляция, вытяжка, приток, зонты, вентиляторы"
        }
      ]
    },
    "ventilyatsiya": {
      "badge": "ВЕНТИЛЯЦИЯ КУХНИ",
      "title": "Быстрый выбор по вентиляции ресторана",
      "description": "Если понятно, что проблема в вытяжке, притоке, запахе, дыме или вентиляторе, переходите сразу на точную страницу.",
      "action": {
        "href": "remont-ventilyatsii-restoranov.html",
        "label": "Ремонт вентиляции",
        "icon": "ri-arrow-right-line"
      },
      "cards": [
        {
          "href": "ventilyatsiya-restorana-ne-tyanet.html",
          "title": "Вентиляция не тянет",
          "description": "Слабая тяга, дым, жар, запахи"
        },
        {
          "href": "remont-vytyazhki-restorana.html",
          "title": "Ремонт вытяжки",
          "description": "Зонт, вентилятор, воздуховоды, фильтры"
        },
        {
          "href": "chistka-ventilyatsii-restoranov.html",
          "title": "Чистка вентиляции",
          "description": "Жир, налёт, засор, падение тяги"
        },
        {
          "href": "avtomatika-ventilyatsii-restorana.html",
          "title": "Автоматика",
          "description": "Щит, пуск, датчики, частотник"
        }
      ]
    }
  },
  "navigationGroups": [
    {
      "label": "Основное оборудование",
      "items": [
        {
          "href": "parokonvektomaty.html",
          "icon": "🔥",
          "name": "Пароконвектоматы"
        },
        {
          "href": "plity-pechi.html",
          "icon": "🍳",
          "name": "Плиты и печи"
        },
        {
          "href": "pishevarochnye-kotly.html",
          "icon": "🥘",
          "name": "Пищеварочные котлы"
        },
        {
          "href": "posudomoechnye-mashiny.html",
          "icon": "🍽️",
          "name": "Посудомоечные машины"
        },
        {
          "href": "holodilnoe-oborudovanie.html",
          "icon": "❄️",
          "name": "Холодильное оборудование"
        },
        {
          "href": "ventilyatsiya-restoranov.html",
          "icon": "🌬️",
          "name": "Вентиляция ресторанов"
        }
      ]
    },
    {
      "label": "Другие направления",
      "items": [
        {
          "href": "grili-mangaly.html",
          "icon": "♨️",
          "name": "Грили и фритюр"
        },
        {
          "href": "ice-machines.html",
          "icon": "🧊",
          "name": "Льдогенераторы"
        },
        {
          "href": "remont-kutterov.html",
          "icon": "🔪",
          "name": "Профессиональные куттеры"
        },
        {
          "href": "remont-sous-vide.html",
          "icon": "🌡️",
          "name": "Оборудование sous-vide"
        }
      ]
    }
  ],
  "footerGroups": [
    {
      "title": "Основные направления",
      "items": [
        {
          "href": "uslugi.html",
          "label": "Каталог ремонта оборудования"
        },
        {
          "href": "parokonvektomaty.html",
          "label": "Ремонт пароконвектоматов"
        },
        {
          "href": "plity-pechi.html",
          "label": "Ремонт плит и печей"
        },
        {
          "href": "pishevarochnye-kotly.html",
          "label": "Ремонт пищеварочных котлов"
        },
        {
          "href": "posudomoechnye-mashiny.html",
          "label": "Ремонт посудомоечных машин"
        },
        {
          "href": "holodilnoe-oborudovanie.html",
          "label": "Ремонт холодильного оборудования"
        }
      ]
    },
    {
      "title": "Другие услуги",
      "items": [
        {
          "href": "ventilyatsiya-restoranov.html",
          "label": "Вентиляция ресторанов"
        },
        {
          "href": "grili-mangaly.html",
          "label": "Грили и фритюр"
        },
        {
          "href": "ice-machines.html",
          "label": "Льдогенераторы"
        },
        {
          "href": "remont-kutterov.html",
          "label": "Профессиональные куттеры"
        },
        {
          "href": "remont-sous-vide.html",
          "label": "Оборудование sous-vide"
        },
        {
          "href": "about.html",
          "label": "О компании"
        },
        {
          "href": "contact.html",
          "label": "Контакты"
        }
      ]
    }
  ]
}
